hashlistdict/README.MD
hashlistdict/__init__.py
hashlistdict/requirements.txt
hashlistdict/thirdparty.json
hashlistdict-0.11.dist-info/LICENSE.rst
hashlistdict-0.11.dist-info/METADATA
hashlistdict-0.11.dist-info/WHEEL
hashlistdict-0.11.dist-info/top_level.txt
hashlistdict-0.11.dist-info/RECORD
