Metadata-Version: 2.1
Name: hashlistdict
Version: 0.11
Summary: Hashable dict/list - subclasses of list/dict with a custom hash function based on alternating addition and subtraction of element hashes - pure Python
Home-page: https://github.com/hansalemaos/hashlistdict
Author: Johannes Fischer
Author-email: aulasparticularesdealemaosp@gmail.com
License: MIT
Keywords: nested,list,dict,hash,hashable
Classifier: Development Status :: 4 - Beta
Classifier: Programming Language :: Python :: 3 :: Only
Classifier: Programming Language :: Python :: 3.10
Classifier: Topic :: Software Development :: Libraries :: Python Modules
Classifier: Topic :: Utilities
License-File: LICENSE.rst
Requires-Dist: flatten-any-dict-iterable-or-whatsoever
